Metadata-Version: 1.0
Name: simple-prob-distributions
Version: 1.1.3
Summary: Normal (Gaussian) and Binomial distributions
Home-page: http://pypi.org/pypi/simple-prob-distributions
Author: Haard Shah
Author-email: haard2013@gmail.com
License: license.txt
Platform: UNKNOWN
